flask_sieve/__init__.py
flask_sieve/conditional_inclusion_rules.py
flask_sieve/exceptions.py
flask_sieve/parser.py
flask_sieve/requests.py
flask_sieve/rules_processor.py
flask_sieve/translator.py
flask_sieve/validator.py
flask_sieve/lang/__init__.py
flask_sieve/lang/en.py
tests/__init__.py
tests/test_exceptions.py
tests/test_parser.py
tests/test_requests.py
tests/test_rules_processor.py
tests/test_sieve.py
tests/test_validator.py
flask_sieve-2.0.1.dist-info/LICENSE.txt
flask_sieve-2.0.1.dist-info/METADATA
flask_sieve-2.0.1.dist-info/WHEEL
flask_sieve-2.0.1.dist-info/top_level.txt
flask_sieve-2.0.1.dist-info/RECORD
