Metadata-Version: 2.1
Name: flask-sieve
Version: 2.0.1
Summary: A Laravel inspired requests validator for Flask
Home-page: https://github.com/codingedward/flask-sieve
Author: Edward Njoroge
Author-email: codingedward@gmail.com
Maintainer: Edward Njoroge
Maintainer-email: codingedward@gmail.com
License: BSD-2
Project-URL: Funding, https://donate.pypi.org
Project-URL: Source, https://github.com/codingedward/flask-sieve/
Project-URL: Tracker, https://github.com/codingedward/flask-sieve/issues
Platform: UNKNOWN
Classifier: Development Status :: 5 - Production/Stable
Classifier: Programming Language :: Python :: 3.6
Classifier: Programming Language :: Python :: 3.7
Classifier: Programming Language :: Python :: 3.8
Classifier: Programming Language :: Python :: 3.9
Classifier: Topic :: Software Development :: Libraries :: Python Modules
Requires-Python: >=3.6
License-File: LICENSE.txt
Requires-Dist: Flask
Requires-Dist: Pillow
Requires-Dist: python-dateutil
Requires-Dist: pytz
Requires-Dist: requests
Requires-Dist: filetype
